README.rst
setup.cfg
setup.py
repoq/__init__.py
repoq/backends.py
repoq/handlers.py
repoq/tests.py
repoq.egg-info/PKG-INFO
repoq.egg-info/SOURCES.txt
repoq.egg-info/dependency_links.txt
repoq.egg-info/entry_points.txt
repoq.egg-info/not-zip-safe
repoq.egg-info/requires.txt
repoq.egg-info/top_level.txt