Metadata-Version: 1.0
Name: repoq
Version: 0.0.1
Summary: Collection of utilities to query a repository of python packages
Home-page: UNKNOWN
Author: Bogdan Hodorog
Author-email: bogdan.hodorog@3pillarglobal.com
License: UNKNOWN
Keywords: python repository pypi
Platform: UNKNOWN
Classifier: Development Status :: 3 - Alpha
Classifier: Environment :: Console
Classifier: Intended Audience :: Developers
Classifier: Intended Audience :: System Administrators
Classifier: Topic :: System :: Software Distribution
